MEGABYTE_pytorch/__init__.py
MEGABYTE_pytorch/attend.py
MEGABYTE_pytorch/megabyte.py
MEGABYTE_pytorch-0.3.6.dist-info/LICENSE
MEGABYTE_pytorch-0.3.6.dist-info/METADATA
MEGABYTE_pytorch-0.3.6.dist-info/WHEEL
MEGABYTE_pytorch-0.3.6.dist-info/top_level.txt
MEGABYTE_pytorch-0.3.6.dist-info/RECORD
