Metadata-Version: 2.1
Name: MEGABYTE-pytorch
Version: 0.3.6
Summary: MEGABYTE - Pytorch
Home-page: https://github.com/lucidrains/MEGABYTE-pytorch
Author: Phil Wang
Author-email: lucidrains@gmail.com
License: MIT
Keywords: artificial intelligence,attention mechanism,transformers
Classifier: Development Status :: 4 - Beta
Classifier: Intended Audience :: Developers
Classifier: Topic :: Scientific/Engineering :: Artificial Intelligence
Classifier: License :: OSI Approved :: MIT License
Classifier: Programming Language :: Python :: 3.6
License-File: LICENSE
Requires-Dist: beartype
Requires-Dist: einops>=0.8.0
Requires-Dist: packaging>=21.0
Requires-Dist: torch>=2.3
Requires-Dist: tqdm
